[
  {
    "imageUrl": "/uploads/4cae3fdf-9233-4829-85f5-4b4ffa26ea3c.png",
    "musicUrl": "/uploads/57c243ef-2045-4cbf-b1df-01d905a2e268.mp3",
    "episodes": [
      {
        "id": "8713d11d-18fb-45c3-9756-ebd8a003f67d",
        "title": "Werooom Moom",
        "description": "dadassdsadd",
        "imageAlt": "Werooom Moom",
        "imageUrl": "/uploads/dcce006f-f1c0-4265-ad0e-02c8271f127d.png",
        "panels": [
          {
            "id": "6565ea95-b7c2-4744-9b22-0100a0ef0d48",
            "imageUrl": "/uploads/ad0ebc1b-d1e8-431a-8ee2-73b92b536eaa.png",
            "imageAlt": "Werooom Moom panel 4",
            "order": 0
          },
          {
            "id": "a0591170-fc32-4851-a0ec-3232337266c1",
            "imageUrl": "/uploads/f9c17d33-4a7b-428b-8746-da19e26d872d.png",
            "imageAlt": "Werooom Moom panel 1",
            "order": 1
          },
          {
            "id": "3726a2dd-107f-4338-a20a-3e43b8a2a6d1",
            "imageUrl": "/uploads/11043a54-9348-4219-875f-c177cb034279.png",
            "imageAlt": "Werooom Moom panel 2",
            "order": 2
          },
          {
            "id": "655d3727-7e5e-4859-8ada-d3a8c0186cf3",
            "imageUrl": "/uploads/feb6f483-39ec-4e7b-85a7-e21582ec9b1b.png",
            "imageAlt": "Werooom Moom panel 3",
            "order": 3
          }
        ],
        "createdAt": "2026-06-14T23:43:49.044Z",
        "updatedAt": "2026-06-14T23:55:32.652Z"
      },
      {
        "id": "0210b7e1-aef0-4530-8f22-7841f900be13",
        "title": "Asgdg Sldd",
        "description": "dsdgdsg",
        "imageAlt": "Asgdg Sldd",
        "imageUrl": "/uploads/718b095f-fc23-48d8-bd74-a3eb4525961f.png",
        "panels": [
          {
            "id": "f2891938-4bf1-4484-8bcc-b10e658884fd",
            "imageUrl": "/uploads/08c59e3e-793e-4f1d-96b7-3202438e8461.png",
            "imageAlt": "Asgdg Sldd panel 1",
            "order": 0
          }
        ],
        "createdAt": "2026-06-14T23:43:23.669Z",
        "updatedAt": "2026-06-14T23:43:23.669Z"
      },
      {
        "id": "ede99076-2a92-4150-bf31-f98b6cff0467",
        "title": "The Second Act",
        "description": "The test",
        "imageAlt": "The Second Act",
        "imageUrl": "/uploads/72be885f-d77b-4478-b578-477f46e0da00.gif",
        "panels": [
          {
            "id": "81894a89-578f-4e9f-ae71-88d823455d5f",
            "imageUrl": "/uploads/5e55eea9-898b-47bc-a206-495cb3c71f86.png",
            "imageAlt": "The Second Act panel 1",
            "order": 0
          },
          {
            "id": "8b08e41f-4e1d-4091-be71-10beae970813",
            "imageUrl": "/uploads/019a6fad-47e8-42eb-ad3d-52b6fe09d488.png",
            "imageAlt": "The Second Act panel 2",
            "order": 1
          },
          {
            "id": "a1b73fe0-123a-4f31-9d3e-200c03782882",
            "imageUrl": "/uploads/ab23a951-62bd-450e-8b31-d667c3b10533.png",
            "imageAlt": "The Second Act panel 3",
            "order": 2
          }
        ],
        "createdAt": "2026-06-14T23:42:58.364Z",
        "updatedAt": "2026-06-14T23:42:58.364Z"
      },
      {
        "id": "29c48e5b-4828-4414-bd5f-2bcd514d2b35",
        "title": "The First Act",
        "description": "The beginning of the story.",
        "imageAlt": "The First Act",
        "imageUrl": "/uploads/88d90b56-ea38-4131-b483-008849536bf4.png",
        "panels": [
          {
            "id": "1d884707-c828-4bb7-b906-02aac2d79ae4",
            "imageUrl": "/uploads/43a80198-3af6-43dc-a0e3-f63eb8347ecb.png",
            "imageAlt": "The First Act panel 1",
            "order": 0
          },
          {
            "id": "301bbf17-5f1a-4691-864b-255b2c7e6193",
            "imageUrl": "/uploads/f030b3f0-0965-4c4c-b244-be3c5d1941e7.png",
            "imageAlt": "The First Act panel 2",
            "order": 1
          },
          {
            "id": "9f64e2e9-b36c-4fc6-bb1c-ce6eb721912d",
            "imageUrl": "/uploads/bbe25b80-8a8c-4f2d-ade1-98f50dac02fe.png",
            "imageAlt": "The First Act panel 3",
            "order": 2
          }
        ],
        "createdAt": "2026-06-14T23:33:48.616Z",
        "updatedAt": "2026-06-14T23:41:26.295Z"
      }
    ],
    "comments": [
      {
        "id": "fcb9ef67-cde4-49eb-b6f6-a9ea2efd47c7",
        "userId": "641307116677758976",
        "username": "wobblingbottom",
        "text": "@wobblingbottom dffs",
        "createdAt": "2026-06-15T00:21:36.439Z"
      },
      {
        "id": "ed99815f-4dd3-4b61-8c23-e05609ea3df9",
        "userId": "641307116677758976",
        "username": "wobblingbottom",
        "text": "fsf",
        "createdAt": "2026-06-15T00:21:34.363Z"
      }
    ],
    "ratings": [
      {
        "id": "d9cc0d07-2d96-41e7-8c52-f0d717370e31",
        "userId": "641307116677758976",
        "username": "wobblingbottom",
        "rating": 4,
        "createdAt": "2026-06-14T23:34:07.840Z",
        "updatedAt": "2026-06-15T00:21:31.071Z"
      }
    ],
    "rating": 0,
    "id": "72a42fd2-4190-41e3-af79-5d1dcd07eb06",
    "title": "The Big Craze Theory",
    "description": "The birth of the land of the patients.",
    "status": "published",
    "imageAlt": "Placeholder image",
    "createdAt": "2026-06-14T23:32:47.430Z",
    "updatedAt": "2026-06-14T23:55:32.652Z"
  }
]